/*
** $Id: lopcodes.h $
** Opcodes for Lua virtual machine
** See Copyright Notice in lua.h
*/

#ifndef lopcodes_h
#define lopcodes_h

#include "llimits.h"


/*================================================================
  We assume that instructions are unsigned 64-bit integers.
  All instructions have an opcode in the first 9 bits.
  Instructions can have the following formats:

        6 6 6 6 6 6 6 6 6 6 5 5 5 5 5 5 5 5 5 5 4 4 4 4 4 4 4 4 4 4 3 3 3 3 3 3 3 3 3 3 2 2 2 2 2 2 2 2 2 2 1 1 1 1 1 1 1 1 1 1 0 0 0 0 0 0 0 0 0 0
        3 2 1 0 9 8 7 6 5 4 3 2 1 0 9 8 7 6 5 4 3 2 1 0 9 8 7 6 5 4 3 2 1 0 9 8 7 6 5 4 3 2 1 0 9 8 7 6 5 4 3 2 1 0 9 8 7 6 5 4 3 2 1 0
iABC          C(16)     |      B(16)    |k|     A(16)      |   Op(9)     |
ivABC         vC(20)     |     vB(14)   |k|     A(16)      |   Op(9)     |
iABx                Bx(33)               |     A(16)      |   Op(9)     |
iAsBx              sBx (signed)(33)      |     A(16)      |   Op(9)     |
iAx                           Ax(49)                     |   Op(9)     |
isJ                           sJ (signed)(49)            |   Op(9)     |

  ('v' stands for "variant", 's' for "signed", 'x' for "extended.")
  A signed argument is represented in excess K: The represented value is
  the written unsigned value minus K, where K is half (rounded down) the
  maximum value for the corresponding unsigned argument.
================================================================*/


/* basic instruction formats */
enum OpMode {iABC, ivABC, iABx, iAsBx, iAx, isJ};


/*
** size and position of opcode arguments.
** Custom Scrambled 64-bit Layout for complete obfuscation
*/
#define SIZE_OP		10
#define SIZE_A		15
#define SIZE_C		15
#define SIZE_B		15
#define SIZE_vB		14
#define SIZE_vC		16

#define SIZE_Bx		(SIZE_C + SIZE_B + 1)  /* 31 */
#define SIZE_Ax		(SIZE_Bx + SIZE_A)     /* 46 */
#define SIZE_sJ		(SIZE_Bx + SIZE_A)     /* 46 */

/*
** New bitfield positions.
** We place OP at the top to allow huge contiguous spaces for Ax, sJ, Bx.
** Total used bits for iABC: OP(10) + A(15) + C(15) + B(15) + k(1) = 56 bits.
** Layout (from LSB to MSB):
**   0-14:  A   (15 bits)
**   15-29: B   (15 bits)
**   30:    k   (1 bit)
**   31-45: C   (15 bits)
**   ... (gap)
**   54-63: OP  (10 bits)
*/
#define POS_A		0
#define POS_B		(POS_A + SIZE_A)
#define POS_k		(POS_B + SIZE_B)
#define POS_C		(POS_k + 1)
#define POS_OP		54

#define POS_vB		POS_B
#define POS_vC		POS_C

#define POS_Bx		POS_B
#define POS_Ax		POS_A
#define POS_sJ		POS_A


/*
** limits for opcode arguments.
** we use (signed) 'int' to manipulate most arguments,
** so they must fit in ints.
*/

/*
** Check whether type 'int' has at least 'b' + 1 bits.
** 'b' < 32; +1 for the sign bit.
*/
#define L_INTHASBITS(b)		((UINT_MAX >> (b)) >= 1)


#if L_INTHASBITS(SIZE_Bx)
#define MAXARG_Bx	((1LL<<SIZE_Bx)-1)
#else
#define MAXARG_Bx	MAX_INT
#endif

#define OFFSET_sBx	(MAXARG_Bx>>1)         /* 'sBx' is signed */


#if L_INTHASBITS(SIZE_Ax)
#define MAXARG_Ax	((1LL<<SIZE_Ax)-1)
#else
#define MAXARG_Ax	MAX_INT
#endif

#if L_INTHASBITS(SIZE_sJ)
#define MAXARG_sJ	((1LL << SIZE_sJ) - 1)
#else
#define MAXARG_sJ	MAX_INT
#endif

#define OFFSET_sJ	(MAXARG_sJ >> 1)


#define MAXARG_A	((1<<SIZE_A)-1)
#define MAXARG_B	((1<<SIZE_B)-1)
#define MAXARG_vB	((1<<SIZE_vB)-1)
#define MAXARG_C	((1<<SIZE_C)-1)
#define MAXARG_vC	((1<<SIZE_vC)-1)
#define OFFSET_sC	(MAXARG_C >> 1)

#define int2sC(i)	((i) + OFFSET_sC)
#define sC2int(i)	((i) - OFFSET_sC)


/* creates a mask with 'n' 1 bits at position 'p' */
#define MASK1(n,p)	((~((~(Instruction)0)<<(n)))<<(p))

/* creates a mask with 'n' 0 bits at position 'p' */
#define MASK0(n,p)	(~MASK1(n,p))

/*
** the following macros help to manipulate instructions
*/

#define GET_OPCODE(i)	(cast(OpCode, ((i)>>POS_OP) & MASK1(SIZE_OP,0)))
#define SET_OPCODE(i,o)	((i) = (((i)&MASK0(SIZE_OP,POS_OP)) | \
		((cast(Instruction, o)<<POS_OP)&MASK1(SIZE_OP,POS_OP))))

#define checkopm(i,m)	(getOpMode(GET_OPCODE(i)) == m)


#define getarg(i,pos,size)	(cast_int(((i)>>(pos)) & MASK1(size,0)))
#define setarg(i,v,pos,size)	((i) = (((i)&MASK0(size,pos)) | \
                ((cast(Instruction, v)<<pos)&MASK1(size,pos))))

#define GETARG_A(i)	getarg(i, POS_A, SIZE_A)
#define SETARG_A(i,v)	setarg(i, v, POS_A, SIZE_A)

#define GETARG_B(i)  \
	check_exp(checkopm(i, iABC), getarg(i, POS_B, SIZE_B))
#define GETARG_vB(i)  \
	check_exp(checkopm(i, ivABC), getarg(i, POS_vB, SIZE_vB))
#define GETARG_sB(i)	sC2int(GETARG_B(i))
#define SETARG_B(i,v)	setarg(i, v, POS_B, SIZE_B)
#define SETARG_vB(i,v)	setarg(i, v, POS_vB, SIZE_vB)

#define GETARG_C(i)  \
	check_exp(checkopm(i, iABC), getarg(i, POS_C, SIZE_C))
#define GETARG_vC(i)  \
	check_exp(checkopm(i, ivABC), getarg(i, POS_vC, SIZE_vC))
#define GETARG_sC(i)	sC2int(GETARG_C(i))
#define SETARG_C(i,v)	setarg(i, v, POS_C, SIZE_C)
#define SETARG_vC(i,v)	setarg(i, v, POS_vC, SIZE_vC)

#define TESTARG_k(i)	check_exp(checkopm(i, iABC), (cast_int(((i) & (1u << POS_k)))))
#define GETARG_k(i)	check_exp(checkopm(i, iABC), getarg(i, POS_k, 1))
#define SETARG_k(i,v)	setarg(i, v, POS_k, 1)

#define GETARG_Bx(i)	check_exp(checkopm(i, iABx), getarg(i, POS_Bx, SIZE_Bx))
#define SETARG_Bx(i,v)	setarg(i, v, POS_Bx, SIZE_Bx)

#define GETARG_Ax(i)	check_exp(checkopm(i, iAx), getarg(i, POS_Ax, SIZE_Ax))
#define SETARG_Ax(i,v)	setarg(i, v, POS_Ax, SIZE_Ax)

#define GETARG_sBx(i)  \
	check_exp(checkopm(i, iAsBx), getarg(i, POS_Bx, SIZE_Bx) - OFFSET_sBx)
#define SETARG_sBx(i,b)	SETARG_Bx((i),cast_uint((b)+OFFSET_sBx))

#define GETARG_sJ(i)  \
	check_exp(checkopm(i, isJ), getarg(i, POS_sJ, SIZE_sJ) - OFFSET_sJ)
#define SETARG_sJ(i,j) \
	setarg(i, cast_uint((j)+OFFSET_sJ), POS_sJ, SIZE_sJ)


#define CREATE_ABCk(o,a,b,c,k)	((cast(Instruction, o)<<POS_OP) \
			| (cast(Instruction, a)<<POS_A) \
			| (cast(Instruction, b)<<POS_B) \
			| (cast(Instruction, c)<<POS_C) \
			| (cast(Instruction, k)<<POS_k))

#define CREATE_vABCk(o,a,b,c,k)	((cast(Instruction, o)<<POS_OP) \
			| (cast(Instruction, a)<<POS_A) \
			| (cast(Instruction, b)<<POS_vB) \
			| (cast(Instruction, c)<<POS_vC) \
			| (cast(Instruction, k)<<POS_k))

#define CREATE_ABx(o,a,bc)	((cast(Instruction, o)<<POS_OP) \
			| (cast(Instruction, a)<<POS_A) \
			| (cast(Instruction, bc)<<POS_Bx))

#define CREATE_Ax(o,a)		((cast(Instruction, o)<<POS_OP) \
			| (cast(Instruction, a)<<POS_Ax))

#define CREATE_sJ(o,j,k)	((cast(Instruction, o) << POS_OP) \
			| (cast(Instruction, j) << POS_sJ) \
			| (cast(Instruction, k) << POS_k))


#if !defined(MAXINDEXRK)  /* (for debugging only) */
#define MAXINDEXRK	MAXARG_B
#endif


/*
** Maximum size for the stack of a Lua function. It must fit in 8 bits.
** The highest valid register is one less than this value.
*/
#define MAX_FSTACK	MAXARG_A

/*
** Invalid register (one more than last valid register).
*/
#define NO_REG		MAX_FSTACK



/*
** R[x] - register
** K[x] - constant (in constant table)
** RK(x) == if k(i) then K[x] else R[x]
*/


/*
** Grep "ORDER OP" if you change this enum.
** See "Notes" below for more information about some instructions.
*/

typedef enum {
/*----------------------------------------------------------------------
  name		args	description
------------------------------------------------------------------------*/
OP_MOVE,/*	A B	R[A] := R[B]					*/
OP_LOADI,/*	A sBx	R[A] := sBx					*/
OP_LOADF,/*	A sBx	R[A] := (lua_Number)sBx				*/
OP_LOADK,/*	A Bx	R[A] := K[Bx]					*/
OP_LOADKX,/*	A	R[A] := K[extra arg]				*/
OP_LOADFALSE,/*	A	R[A] := false					*/
OP_LFALSESKIP,/*A	R[A] := false; pc++				*/
OP_LOADTRUE,/*	A	R[A] := true					*/
OP_LOADNIL,/*	A B	R[A], R[A+1], ..., R[A+B] := nil		*/
OP_GETUPVAL,/*	A B	R[A] := UpValue[B]				*/
OP_SETUPVAL,/*	A B	UpValue[B] := R[A]				*/

OP_GETTABUP,/*	A B C	R[A] := UpValue[B][K[C]:shortstring]		*/
OP_GETTABLE,/*	A B C	R[A] := R[B][R[C]]				*/
OP_GETI,/*	A B C	R[A] := R[B][C]					*/
OP_GETFIELD,/*	A B C	R[A] := R[B][K[C]:shortstring]			*/

OP_SETTABUP,/*	A B C	UpValue[A][K[B]:shortstring] := RK(C)		*/
OP_SETTABLE,/*	A B C	R[A][R[B]] := RK(C)				*/
OP_SETI,/*	A B C	R[A][B] := RK(C)				*/
OP_SETFIELD,/*	A B C	R[A][K[B]:shortstring] := RK(C)			*/

OP_NEWTABLE,/*	A vB vC k	R[A] := {}				*/

OP_SELF,/*	A B C	R[A+1] := R[B]; R[A] := R[B][K[C]:shortstring]	*/

OP_ADDI,/*	A B sC	R[A] := R[B] + sC				*/

OP_ADDK,/*	A B C	R[A] := R[B] + K[C]:number			*/
OP_SUBK,/*	A B C	R[A] := R[B] - K[C]:number			*/
OP_MULK,/*	A B C	R[A] := R[B] * K[C]:number			*/
OP_MODK,/*	A B C	R[A] := R[B] % K[C]:number			*/
OP_POWK,/*	A B C	R[A] := R[B] ^ K[C]:number			*/
OP_DIVK,/*	A B C	R[A] := R[B] / K[C]:number			*/
OP_IDIVK,/*	A B C	R[A] := R[B] // K[C]:number			*/

OP_BANDK,/*	A B C	R[A] := R[B] & K[C]:integer			*/
OP_BORK,/*	A B C	R[A] := R[B] | K[C]:integer			*/
OP_BXORK,/*	A B C	R[A] := R[B] ~ K[C]:integer			*/

OP_SHLI,/*	A B sC	R[A] := sC << R[B]				*/
OP_SHRI,/*	A B sC	R[A] := R[B] >> sC				*/

OP_ADD,/*	A B C	R[A] := R[B] + R[C]				*/
OP_SUB,/*	A B C	R[A] := R[B] - R[C]				*/
OP_MUL,/*	A B C	R[A] := R[B] * R[C]				*/
OP_MOD,/*	A B C	R[A] := R[B] % R[C]				*/
OP_POW,/*	A B C	R[A] := R[B] ^ R[C]				*/
OP_DIV,/*	A B C	R[A] := R[B] / R[C]				*/
OP_IDIV,/*	A B C	R[A] := R[B] // R[C]				*/

OP_BAND,/*	A B C	R[A] := R[B] & R[C]				*/
OP_BOR,/*	A B C	R[A] := R[B] | R[C]				*/
OP_BXOR,/*	A B C	R[A] := R[B] ~ R[C]				*/
OP_SHL,/*	A B C	R[A] := R[B] << R[C]				*/
OP_SHR,/*	A B C	R[A] := R[B] >> R[C]				*/

OP_SPACESHIP,/*	A B C	R[A] := R[B] <=> R[C] (返回-1,0,1)		*/

OP_MMBIN,/*	A B C	call C metamethod over R[A] and R[B]		*/
OP_MMBINI,/*	A sB C k	call C metamethod over R[A] and sB	*/
OP_MMBINK,/*	A B C k		call C metamethod over R[A] and K[B]	*/

OP_UNM,/*	A B	R[A] := -R[B]					*/
OP_BNOT,/*	A B	R[A] := ~R[B]					*/
OP_NOT,/*	A B	R[A] := not R[B]				*/
OP_LEN,/*	A B	R[A] := #R[B] (length operator)			*/

OP_CONCAT,/*	A B	R[A] := R[A].. ... ..R[A + B - 1]		*/

OP_CLOSE,/*	A	close all upvalues >= R[A]			*/
OP_TBC,/*	A	mark variable A "to be close"			*/
OP_JMP,/*	sJ	pc += sJ					*/
OP_EQ,/*	A B k	if ((R[A] == R[B]) ~= k) then pc++		*/
OP_LT,/*	A B k	if ((R[A] <  R[B]) ~= k) then pc++		*/
OP_LE,/*	A B k	if ((R[A] <= R[B]) ~= k) then pc++		*/

OP_EQK,/*	A B k	if ((R[A] == K[B]) ~= k) then pc++		*/
OP_EQI,/*	A sB k	if ((R[A] == sB) ~= k) then pc++		*/
OP_LTI,/*	A sB k	if ((R[A] < sB) ~= k) then pc++			*/
OP_LEI,/*	A sB k	if ((R[A] <= sB) ~= k) then pc++		*/
OP_GTI,/*	A sB k	if ((R[A] > sB) ~= k) then pc++			*/
OP_GEI,/*	A sB k	if ((R[A] >= sB) ~= k) then pc++		*/

OP_TEST,/*	A k	if (not R[A] == k) then pc++			*/
OP_TESTSET,/*	A B k	if (not R[B] == k) then pc++ else R[A] := R[B]  */


OP_CALL,/*	A B C	R[A], ... ,R[A+C-2] := R[A](R[A+1], ... ,R[A+B-1]) */
OP_TAILCALL,/*	A B C k	return R[A](R[A+1], ... ,R[A+B-1])		*/

OP_RETURN,/*	A B C k	return R[A], ... ,R[A+B-2]			*/
OP_RETURN0,/*		return						*/
OP_RETURN1,/*	A	return R[A]					*/

OP_FORLOOP,/*	A Bx	update counters; if loop continues then pc-=Bx; */
OP_FORPREP,/*	A Bx	<check values and prepare counters>;
                        if not to run then pc+=Bx+1;			*/

OP_TFORPREP,/*	A Bx	create upvalue for R[A + 3]; pc+=Bx		*/
OP_TFORCALL,/*	A C	R[A+4], ... ,R[A+3+C] := R[A](R[A+1], R[A+2]);	*/
OP_TFORLOOP,/*	A Bx	if R[A+2] ~= nil then { R[A]=R[A+2]; pc -= Bx }	*/

OP_SETLIST,/*	A vB vC k	R[A][vC+i] := R[A+i], 1 <= i <= vB	*/

OP_CLOSURE,/*	A Bx	R[A] := closure(KPROTO[Bx])			*/

OP_VARARG,/*	A B C k	R[A], ..., R[A+C-2] = varargs  			*/

OP_GETVARG, /*	A B C	R[A] := R[B][R[C]], R[B] is vararg parameter    */

OP_ERRNNIL,/*	A Bx	raise error if R[A] ~= nil (K[Bx - 1] is global name)*/

OP_VARARGPREP,/* 	(adjust varargs)				*/

OP_IS,/*	A B C k	if ((type(R[A]) == K[B]) ~= k) then pc++	*/

OP_TESTNIL,/*	A B k	if (R[B] is nil) == k then pc++ else R[A] := R[B]	*/

/*----------------------------------------------------------------------
  面向对象系统操作码
------------------------------------------------------------------------*/
OP_NEWCLASS,/*	A Bx	R[A] := 创建新类，类名为K[Bx]			*/
OP_INHERIT,/*	A B	R[A].__parent := R[B]，设置类继承关系		*/
OP_GETSUPER,/*	A B C	R[A] := R[B].__parent[K[C]:shortstring]	调用父类方法	*/
OP_SETMETHOD,/*	A B C	R[A][K[B]:shortstring] := R[C]，设置类方法		*/
OP_SETSTATIC,/*	A B C	R[A].__static[K[B]:shortstring] := R[C]，设置静态成员	*/
OP_NEWOBJ,/*	A B C	R[A] := R[B]()，使用R[B]类创建新对象，参数C个	*/
OP_GETPROP,/*	A B C	R[A] := R[B][K[C]:shortstring]，获取属性（考虑继承链）*/
OP_SETPROP,/*	A B C	R[A][K[B]:shortstring] := RK(C)，设置对象属性	*/
OP_INSTANCEOF,/*A B C k	if ((R[A] instanceof R[B]) ~= k) then pc++	*/
OP_IMPLEMENT,/*	A B	R[A] implements R[B]，类实现接口			*/
OP_SETIFACEFLAG,/*A	设置R[A]为接口（设置CLASS_FLAG_INTERFACE）	*/
OP_ADDMETHOD,/*	A B C	R[A].__methods[K[B]] := K[C]，添加接口方法签名	*/

OP_IN,/*	A B C	R[A] := R[B] in R[C]				*/

/*----------------------------------------------------------------------
  切片操作码 - 支持 Python 风格的切片语法 t[start:end:step]
------------------------------------------------------------------------*/
OP_SLICE,/*	A B C	R[A] := slice(R[B], R[B+1], R[B+2], R[B+3])
			B = 源表寄存器
			B+1 = start (起始索引，nil表示1)
			B+2 = end (结束索引，nil表示#t)
			B+3 = step (步长，nil表示1)
			C = 标志位：0=普通切片，1=有步长		*/

OP_NOP,/*	A B C	空操作指令 - 不执行任何操作
			用于控制流混淆占位，A/B/C参数可携带虚假数据干扰反编译
			A = 虚假寄存器索引（被忽略）
			B = 虚假操作数1（被忽略）
			C = 虚假操作数2（被忽略）			*/

OP_CASE,/*	A B C	R[A] := { R[B], R[C] } (create case pair)	*/

OP_NEWCONCEPT,/*	A Bx	R[A] := concept(KPROTO[Bx])			*/

OP_NEWNAMESPACE,/*	A Bx	R[A] := newnamespace(K[Bx])			*/

OP_LINKNAMESPACE,/*	A B	R[A]->using_next = R[B]				*/

OP_NEWSUPER,/*	A Bx	R[A] := newsuperstruct(K[Bx])			*/

OP_SETSUPER,/*	A B C	R[A][B] := R[C]					*/

OP_GETCMDS,/*	A	R[A] := LXC_CMDS				*/
OP_GETOPS,/*	A	R[A] := LXC_OPERATORS				*/
OP_ASYNCWRAP,/*	A B	R[A] := async_wrap(R[B])			*/
OP_GENERICWRAP,/* A B	R[A] := generic_wrap(R[B], R[B+1], R[B+2])	*/
OP_CHECKTYPE,/*	A B C	if (check_type(R[A], R[B]) != true) error(K[C])	*/

OP_EXTRAARG/*	Ax	extra (larger) argument for previous opcode	*/
} OpCode;


#define NUM_OPCODES	((int)(OP_EXTRAARG) + 1)



/*================================================================
  Notes:

  (*) Opcode OP_LFALSESKIP is used to convert a condition to a boolean
  value, in a code equivalent to (not cond ? false : true).  (It
  produces false and skips the next instruction producing true.)

  (*) Opcodes OP_MMBIN and variants follow each arithmetic and
  bitwise opcode. If the operation succeeds, it skips this next
  opcode. Otherwise, this opcode calls the corresponding metamethod.

  (*) Opcode OP_TESTSET is used in short-circuit expressions that need
  both to jump and to produce a value, such as (a = b or c).

  (*) In OP_CALL, if (B == 0) then B = top - A. If (C == 0), then
  'top' is set to last_result+1, so next open instruction (OP_CALL,
  OP_RETURN*, OP_SETLIST) may use 'top'.

  (*) In OP_VARARG, if (C == 0) then use actual number of varargs and
  set top (like in OP_CALL with C == 0). 'k' means function has a
  vararg table, which is in R[B].

  (*) In OP_RETURN, if (B == 0) then return up to 'top'.

  (*) In OP_LOADKX and OP_NEWTABLE, the next instruction is always
  OP_EXTRAARG.

  (*) In OP_SETLIST, if (B == 0) then real B = 'top'; if k, then
  real C = EXTRAARG _ C (the bits of EXTRAARG concatenated with the
  bits of C).

  (*) In OP_NEWTABLE, vB is log2 of the hash size (which is always a
  power of 2) plus 1, or zero for size zero. If not k, the array size
  is vC. Otherwise, the array size is EXTRAARG _ vC.

  (*) In OP_ERRNNIL, (Bx == 0) means index of global name doesn't
  fit in Bx. (So, that name is not available for the error message.)

  (*) For comparisons, k specifies what condition the test should accept
  (true or false).

  (*) In OP_MMBINI/OP_MMBINK, k means the arguments were flipped
  (the constant is the first operand).

  (*) All comparison and test instructions assume that the instruction
  being skipped (pc++) is a jump.

  (*) In instructions OP_RETURN/OP_TAILCALL, 'k' specifies that the
  function builds upvalues, which may need to be closed. C > 0 means
  the function has hidden vararg arguments, so that its 'func' must be
  corrected before returning; in this case, (C - 1) is its number of
  fixed parameters.

  (*) In comparisons with an immediate operand, C signals whether the
  original operand was a float. (It must be corrected in case of
  metamethods.)

================================================================*/


/*
** masks for instruction properties. The format is:
** bits 0-2: op mode
** bit 3: instruction set register A
** bit 4: operator is a test (next instruction must be a jump)
** bit 5: instruction uses 'L->top' set by previous instruction (when B == 0)
** bit 6: instruction sets 'L->top' for next instruction (when C == 0)
** bit 7: instruction is an MM instruction (call a metamethod)
*/

LUAI_DDEC(const lu_byte luaP_opmodes[NUM_OPCODES];)

#define getOpMode(m)	(cast(enum OpMode, luaP_opmodes[m] & 7))
#define testAMode(m)	(luaP_opmodes[m] & (1 << 3))
#define testTMode(m)	(luaP_opmodes[m] & (1 << 4))
#define testITMode(m)	(luaP_opmodes[m] & (1 << 5))
#define testOTMode(m)	(luaP_opmodes[m] & (1 << 6))
#define testMMMode(m)	(luaP_opmodes[m] & (1 << 7))

/* "out top" (set top for next instruction) */
#define isOT(i)  \
	((testOTMode(GET_OPCODE(i)) && GETARG_C(i) == 0) || \
          GET_OPCODE(i) == OP_TAILCALL)

/* "in top" (uses top from previous instruction) */
#define isIT(i)		(testITMode(GET_OPCODE(i)) && GETARG_B(i) == 0)

#define opmode(mm,ot,it,t,a,m)  \
    (((mm) << 7) | ((ot) << 6) | ((it) << 5) | ((t) << 4) | ((a) << 3) | (m))

LUAI_FUNC int luaP_isOT (Instruction i);
LUAI_FUNC int luaP_isIT (Instruction i);

/* number of list items to accumulate before a SETLIST instruction */
#define LFIELDS_PER_FLUSH	50

#endif
